frpclnt/__init__.py
frpclnt/client.py
frpclnt/exceptions.py
frpclnt/utils.py
frpclnt-0.4.4.dist-info/METADATA
frpclnt-0.4.4.dist-info/WHEEL
frpclnt-0.4.4.dist-info/RECORD
