Metadata-Version: 2.3
Name: frpclnt
Version: 0.4.4
Summary: A universal REST client for FastAPI projects
License: MIT
Author: Aleksandr Yurlov
Author-email: Sasha.yur@mail.ru
Requires-Python: >=3.10,<4.0
Classifier: License :: OSI Approved :: MIT License
Classifier: Programming Language :: Python :: 3
Classifier: Programming Language :: Python :: 3.10
Classifier: Programming Language :: Python :: 3.11
Classifier: Programming Language :: Python :: 3.12
Classifier: Programming Language :: Python :: 3.13
Requires-Dist: aiohttp (>=3.11.6,<4.0.0)
